banner_haramss/__init__.py
banner_haramss/banner.py
banner_HaramSs-0.4.0.dist-info/METADATA
banner_HaramSs-0.4.0.dist-info/WHEEL
banner_HaramSs-0.4.0.dist-info/entry_points.txt
banner_HaramSs-0.4.0.dist-info/top_level.txt
banner_HaramSs-0.4.0.dist-info/RECORD
