Metadata-Version: 2.1
Name: banner_HaramSs
Version: 0.4.0
Summary: Banner Output Program
Author-email: HaramSs <haram8274@gmail.com>
License: MIT
Project-URL: Homepage, https://github.com/HaramSs/python
Project-URL: Issues, https://github.com/HaramSs/python/issues
Requires-Python: >=3.9
Requires-Dist: pyfiglet >=1.0.2
